{
    "annotations": [
        {
            "bbox": [
                166.0,
                140.0,
                99.0,
                169.0
            ],
            "is_occluded": false,
            "attributes": {},
            "iscrowd": 0,
            "segmentation": null,
            "id": 0,
            "category_id": 1,
            "area": 16731.0,
            "image_id": 0
        },
        {
            "bbox": [
                378.0,
                147.0,
                94.0,
                172.0
            ],
            "is_occluded": false,
            "attributes": {},
            "iscrowd": 0,
            "segmentation": null,
            "id": 1,
            "category_id": 1,
            "area": 16168.0,
            "image_id": 0
        },
        {
            "bbox": [
                94.0,
                69.0,
                146.0,
                82.0
            ],
            "is_occluded": false,
            "attributes": {},
            "iscrowd": 0,
            "segmentation": null,
            "id": 2,
            "category_id": 1,
            "area": 11972.0,
            "image_id": 1
        },
        {
            "bbox": [
                393.0,
                111.0,
                95.0,
                138.0
            ],
            "is_occluded": false,
            "attributes": {},
            "iscrowd": 0,
            "segmentation": null,
            "id": 3,
            "category_id": 1,
            "area": 13110.0,
            "image_id": 1
        },
        {
            "bbox": [
                257.0,
                143.0,
                73.0,
                145.0
            ],
            "is_occluded": false,
            "attributes": {},
            "iscrowd": 0,
            "segmentation": null,
            "id": 4,
            "category_id": 1,
            "area": 10585.0,
            "image_id": 2
        },
        {
            "bbox": [
                367.0,
                48.0,
                141.0,
                179.0
            ],
            "is_occluded": false,
            "attributes": {},
            "iscrowd": 0,
            "segmentation": null,
            "id": 5,
            "category_id": 1,
            "area": 25239.0,
            "image_id": 2
        },
        {
            "bbox": [
                189.0,
                1.0,
                173.0,
                138.0
            ],
            "is_occluded": false,
            "attributes": {},
            "iscrowd": 0,
            "segmentation": null,
            "id": 6,
            "category_id": 1,
            "area": 23874.0,
            "image_id": 3
        },
        {
            "bbox": [
                406.0,
                65.0,
                136.0,
                189.0
            ],
            "is_occluded": false,
            "attributes": {},
            "iscrowd": 0,
            "segmentation": null,
            "id": 7,
            "category_id": 1,
            "area": 25704.0,
            "image_id": 3
        },
        {
            "bbox": [
                132.0,
                1.0,
                121.0,
                76.0
            ],
            "is_occluded": false,
            "attributes": {},
            "iscrowd": 0,
            "segmentation": null,
            "id": 8,
            "category_id": 1,
            "area": 9196.0,
            "image_id": 4
        },
        {
            "bbox": [
                407.0,
                1.0,
                103.0,
                54.0
            ],
            "is_occluded": false,
            "attributes": {},
            "iscrowd": 0,
            "segmentation": null,
            "id": 9,
            "category_id": 1,
            "area": 5562.0,
            "image_id": 4
        },
        {
            "bbox": [
                286.0,
                112.0,
                97.0,
                47.0
            ],
            "is_occluded": false,
            "attributes": {},
            "iscrowd": 0,
            "segmentation": null,
            "id": 10,
            "category_id": 1,
            "area": 4559.0,
            "image_id": 5
        },
        {
            "bbox": [
                410.0,
                104.0,
                105.0,
                61.0
            ],
            "is_occluded": false,
            "attributes": {},
            "iscrowd": 0,
            "segmentation": null,
            "id": 11,
            "category_id": 1,
            "area": 6405.0,
            "image_id": 5
        },
        {
            "bbox": [
                209.0,
                102.0,
                211.0,
                122.0
            ],
            "is_occluded": false,
            "attributes": {},
            "iscrowd": 0,
            "segmentation": null,
            "id": 12,
            "category_id": 1,
            "area": 25742.0,
            "image_id": 6
        },
        {
            "bbox": [
                327.0,
                282.0,
                175.0,
                78.0
            ],
            "is_occluded": false,
            "attributes": {},
            "iscrowd": 0,
            "segmentation": null,
            "id": 13,
            "category_id": 1,
            "area": 13650.0,
            "image_id": 6
        },
        {
            "bbox": [
                217.0,
                142.0,
                53.0,
                81.0
            ],
            "is_occluded": false,
            "attributes": {},
            "iscrowd": 0,
            "segmentation": null,
            "id": 14,
            "category_id": 1,
            "area": 4293.0,
            "image_id": 7
        },
        {
            "bbox": [
                320.0,
                125.0,
                54.0,
                84.0
            ],
            "is_occluded": false,
            "attributes": {},
            "iscrowd": 0,
            "segmentation": null,
            "id": 15,
            "category_id": 1,
            "area": 4536.0,
            "image_id": 7
        },
        {
            "bbox": [
                168.0,
                40.0,
                85.0,
                132.0
            ],
            "is_occluded": false,
            "attributes": {},
            "iscrowd": 0,
            "segmentation": null,
            "id": 16,
            "category_id": 1,
            "area": 11220.0,
            "image_id": 8
        },
        {
            "bbox": [
                381.0,
                74.0,
                121.0,
                98.0
            ],
            "is_occluded": false,
            "attributes": {},
            "iscrowd": 0,
            "segmentation": null,
            "id": 17,
            "category_id": 1,
            "area": 11858.0,
            "image_id": 8
        },
        {
            "bbox": [
                92.0,
                270.0,
                157.0,
                89.0
            ],
            "is_occluded": false,
            "attributes": {},
            "iscrowd": 0,
            "segmentation": null,
            "id": 18,
            "category_id": 1,
            "area": 13973.0,
            "image_id": 9
        },
        {
            "bbox": [
                199.0,
                119.0,
                165.0,
                175.0
            ],
            "is_occluded": false,
            "attributes": {},
            "iscrowd": 0,
            "segmentation": null,
            "id": 19,
            "category_id": 1,
            "area": 28875.0,
            "image_id": 9
        },
        {
            "bbox": [
                283.0,
                199.0,
                84.0,
                129.0
            ],
            "is_occluded": false,
            "attributes": {},
            "iscrowd": 0,
            "segmentation": null,
            "id": 20,
            "category_id": 1,
            "area": 10836.0,
            "image_id": 10
        },
        {
            "bbox": [
                382.0,
                1.0,
                110.0,
                113.0
            ],
            "is_occluded": false,
            "attributes": {},
            "iscrowd": 0,
            "segmentation": null,
            "id": 21,
            "category_id": 1,
            "area": 12430.0,
            "image_id": 10
        },
        {
            "bbox": [
                62.0,
                116.0,
                168.0,
                101.0
            ],
            "is_occluded": false,
            "attributes": {},
            "iscrowd": 0,
            "segmentation": null,
            "id": 22,
            "category_id": 1,
            "area": 16968.0,
            "image_id": 11
        },
        {
            "bbox": [
                390.0,
                143.0,
                118.0,
                143.0
            ],
            "is_occluded": false,
            "attributes": {},
            "iscrowd": 0,
            "segmentation": null,
            "id": 23,
            "category_id": 1,
            "area": 16874.0,
            "image_id": 11
        },
        {
            "bbox": [
                212.0,
                115.0,
                81.0,
                156.0
            ],
            "is_occluded": false,
            "attributes": {},
            "iscrowd": 0,
            "segmentation": null,
            "id": 24,
            "category_id": 1,
            "area": 12636.0,
            "image_id": 12
        },
        {
            "bbox": [
                332.0,
                1.0,
                134.0,
                25.0
            ],
            "is_occluded": false,
            "attributes": {},
            "iscrowd": 0,
            "segmentation": null,
            "id": 25,
            "category_id": 1,
            "area": 3350.0,
            "image_id": 12
        },
        {
            "bbox": [
                282.0,
                195.0,
                87.0,
                135.0
            ],
            "is_occluded": false,
            "attributes": {},
            "iscrowd": 0,
            "segmentation": null,
            "id": 26,
            "category_id": 1,
            "area": 11745.0,
            "image_id": 13
        },
        {
            "bbox": [
                380.0,
                1.0,
                115.0,
                115.0
            ],
            "is_occluded": false,
            "attributes": {},
            "iscrowd": 0,
            "segmentation": null,
            "id": 27,
            "category_id": 1,
            "area": 13225.0,
            "image_id": 13
        },
        {
            "bbox": [
                115.0,
                120.0,
                150.0,
                94.0
            ],
            "is_occluded": false,
            "attributes": {},
            "iscrowd": 0,
            "segmentation": null,
            "id": 28,
            "category_id": 1,
            "area": 14100.0,
            "image_id": 14
        },
        {
            "bbox": [
                418.0,
                142.0,
                113.0,
                135.0
            ],
            "is_occluded": false,
            "attributes": {},
            "iscrowd": 0,
            "segmentation": null,
            "id": 29,
            "category_id": 1,
            "area": 15255.0,
            "image_id": 14
        },
        {
            "bbox": [
                224.0,
                118.0,
                56.0,
                80.0
            ],
            "is_occluded": false,
            "attributes": {},
            "iscrowd": 0,
            "segmentation": null,
            "id": 30,
            "category_id": 1,
            "area": 4480.0,
            "image_id": 15
        },
        {
            "bbox": [
                326.0,
                101.0,
                55.0,
                85.0
            ],
            "is_occluded": false,
            "attributes": {},
            "iscrowd": 0,
            "segmentation": null,
            "id": 31,
            "category_id": 1,
            "area": 4675.0,
            "image_id": 15
        },
        {
            "bbox": [
                112.0,
                127.0,
                124.0,
                113.0
            ],
            "is_occluded": false,
            "attributes": {},
            "iscrowd": 0,
            "segmentation": null,
            "id": 32,
            "category_id": 1,
            "area": 14012.0,
            "image_id": 16
        },
        {
            "bbox": [
                342.0,
                96.0,
                104.0,
                90.0
            ],
            "is_occluded": false,
            "attributes": {},
            "iscrowd": 0,
            "segmentation": null,
            "id": 33,
            "category_id": 1,
            "area": 9360.0,
            "image_id": 16
        },
        {
            "bbox": [
                188.0,
                120.0,
                124.0,
                143.0
            ],
            "is_occluded": false,
            "attributes": {},
            "iscrowd": 0,
            "segmentation": null,
            "id": 34,
            "category_id": 1,
            "area": 17732.0,
            "image_id": 17
        },
        {
            "bbox": [
                403.0,
                121.0,
                91.0,
                161.0
            ],
            "is_occluded": false,
            "attributes": {},
            "iscrowd": 0,
            "segmentation": null,
            "id": 35,
            "category_id": 1,
            "area": 14651.0,
            "image_id": 17
        },
        {
            "bbox": [
                275.0,
                99.0,
                75.0,
                132.0
            ],
            "is_occluded": false,
            "attributes": {},
            "iscrowd": 0,
            "segmentation": null,
            "id": 36,
            "category_id": 1,
            "area": 9900.0,
            "image_id": 18
        },
        {
            "bbox": [
                382.0,
                1.0,
                110.0,
                113.0
            ],
            "is_occluded": false,
            "attributes": {},
            "iscrowd": 0,
            "segmentation": null,
            "id": 37,
            "category_id": 1,
            "area": 12430.0,
            "image_id": 18
        },
        {
            "bbox": [
                384.0,
                1.0,
                109.0,
                113.0
            ],
            "is_occluded": false,
            "attributes": {},
            "iscrowd": 0,
            "segmentation": null,
            "id": 38,
            "category_id": 1,
            "area": 12317.0,
            "image_id": 19
        },
        {
            "bbox": [
                283.0,
                197.0,
                86.0,
                132.0
            ],
            "is_occluded": false,
            "attributes": {},
            "iscrowd": 0,
            "segmentation": null,
            "id": 39,
            "category_id": 1,
            "area": 11352.0,
            "image_id": 19
        },
        {
            "bbox": [
                276.0,
                99.0,
                74.0,
                130.0
            ],
            "is_occluded": false,
            "attributes": {},
            "iscrowd": 0,
            "segmentation": null,
            "id": 40,
            "category_id": 1,
            "area": 9620.0,
            "image_id": 20
        },
        {
            "bbox": [
                382.0,
                75.0,
                118.0,
                97.0
            ],
            "is_occluded": false,
            "attributes": {},
            "iscrowd": 0,
            "segmentation": null,
            "id": 41,
            "category_id": 1,
            "area": 11446.0,
            "image_id": 20
        },
        {
            "bbox": [
                202.0,
                114.0,
                55.0,
                80.0
            ],
            "is_occluded": false,
            "attributes": {},
            "iscrowd": 0,
            "segmentation": null,
            "id": 42,
            "category_id": 1,
            "area": 4400.0,
            "image_id": 21
        },
        {
            "bbox": [
                309.0,
                97.0,
                54.0,
                81.0
            ],
            "is_occluded": false,
            "attributes": {},
            "iscrowd": 0,
            "segmentation": null,
            "id": 43,
            "category_id": 1,
            "area": 4374.0,
            "image_id": 21
        },
        {
            "bbox": [
                144.0,
                293.0,
                154.0,
                67.0
            ],
            "is_occluded": false,
            "attributes": {},
            "iscrowd": 0,
            "segmentation": null,
            "id": 44,
            "category_id": 1,
            "area": 10318.0,
            "image_id": 22
        },
        {
            "bbox": [
                254.0,
                142.0,
                173.0,
                174.0
            ],
            "is_occluded": false,
            "attributes": {},
            "iscrowd": 0,
            "segmentation": null,
            "id": 45,
            "category_id": 1,
            "area": 30102.0,
            "image_id": 22
        },
        {
            "bbox": [
                110.0,
                35.0,
                183.0,
                136.0
            ],
            "is_occluded": false,
            "attributes": {},
            "iscrowd": 0,
            "segmentation": null,
            "id": 46,
            "category_id": 1,
            "area": 24888.0,
            "image_id": 23
        },
        {
            "bbox": [
                270.0,
                139.0,
                182.0,
                207.0
            ],
            "is_occluded": false,
            "attributes": {},
            "iscrowd": 0,
            "segmentation": null,
            "id": 47,
            "category_id": 1,
            "area": 37674.0,
            "image_id": 23
        }
    ],
    "images": [
        {
            "license": null,
            "height": 360,
            "date_captured": null,
            "width": 640,
            "dataset": "globalme",
            "id": 0,
            "coco_url": null,
            "flickr_url": null,
            "file_name": "0013.jpg",
            "image": "./img/0013.jpg"
        },
        {
            "license": null,
            "height": 360,
            "date_captured": null,
            "width": 640,
            "dataset": "globalme",
            "id": 1,
            "coco_url": null,
            "flickr_url": null,
            "file_name": "0009.jpg",
            "image": "./img/0009.jpg"
        },
        {
            "license": null,
            "height": 360,
            "date_captured": null,
            "width": 640,
            "dataset": "globalme",
            "id": 2,
            "coco_url": null,
            "flickr_url": null,
            "file_name": "0018.jpg",
            "image": "./img/0018.jpg"
        },
        {
            "license": null,
            "height": 360,
            "date_captured": null,
            "width": 640,
            "dataset": "globalme",
            "id": 3,
            "coco_url": null,
            "flickr_url": null,
            "file_name": "0017.jpg",
            "image": "./img/0017.jpg"
        },
        {
            "license": null,
            "height": 360,
            "date_captured": null,
            "width": 640,
            "dataset": "globalme",
            "id": 4,
            "coco_url": null,
            "flickr_url": null,
            "file_name": "0019.jpg",
            "image": "./img/0019.jpg"
        },
        {
            "license": null,
            "height": 360,
            "date_captured": null,
            "width": 640,
            "dataset": "globalme",
            "id": 5,
            "coco_url": null,
            "flickr_url": null,
            "file_name": "0023.jpg",
            "image": "./img/0023.jpg"
        },
        {
            "license": null,
            "height": 360,
            "date_captured": null,
            "width": 640,
            "dataset": "globalme",
            "id": 6,
            "coco_url": null,
            "flickr_url": null,
            "file_name": "0014.jpg",
            "image": "./img/0014.jpg"
        },
        {
            "license": null,
            "height": 360,
            "date_captured": null,
            "width": 640,
            "dataset": "globalme",
            "id": 7,
            "coco_url": null,
            "flickr_url": null,
            "file_name": "0021.jpg",
            "image": "./img/0021.jpg"
        },
        {
            "license": null,
            "height": 360,
            "date_captured": null,
            "width": 640,
            "dataset": "globalme",
            "id": 8,
            "coco_url": null,
            "flickr_url": null,
            "file_name": "0005.jpg",
            "image": "./img/0005.jpg"
        },
        {
            "license": null,
            "height": 360,
            "date_captured": null,
            "width": 640,
            "dataset": "globalme",
            "id": 9,
            "coco_url": null,
            "flickr_url": null,
            "file_name": "0015.jpg",
            "image": "./img/0015.jpg"
        },
        {
            "license": null,
            "height": 360,
            "date_captured": null,
            "width": 640,
            "dataset": "globalme",
            "id": 10,
            "coco_url": null,
            "flickr_url": null,
            "file_name": "0002.jpg",
            "image": "./img/0002.jpg"
        },
        {
            "license": null,
            "height": 360,
            "date_captured": null,
            "width": 640,
            "dataset": "globalme",
            "id": 11,
            "coco_url": null,
            "flickr_url": null,
            "file_name": "0006.jpg",
            "image": "./img/0006.jpg"
        },
        {
            "license": null,
            "height": 360,
            "date_captured": null,
            "width": 640,
            "dataset": "globalme",
            "id": 12,
            "coco_url": null,
            "flickr_url": null,
            "file_name": "0007.jpg",
            "image": "./img/0007.jpg"
        },
        {
            "license": null,
            "height": 360,
            "date_captured": null,
            "width": 640,
            "dataset": "globalme",
            "id": 13,
            "coco_url": null,
            "flickr_url": null,
            "file_name": "0000.jpg",
            "image": "./img/0000.jpg"
        },
        {
            "license": null,
            "height": 360,
            "date_captured": null,
            "width": 640,
            "dataset": "globalme",
            "id": 14,
            "coco_url": null,
            "flickr_url": null,
            "file_name": "0010.jpg",
            "image": "./img/0010.jpg"
        },
        {
            "license": null,
            "height": 360,
            "date_captured": null,
            "width": 640,
            "dataset": "globalme",
            "id": 15,
            "coco_url": null,
            "flickr_url": null,
            "file_name": "0022.jpg",
            "image": "./img/0022.jpg"
        },
        {
            "license": null,
            "height": 360,
            "date_captured": null,
            "width": 640,
            "dataset": "globalme",
            "id": 16,
            "coco_url": null,
            "flickr_url": null,
            "file_name": "0008.jpg",
            "image": "./img/0008.jpg"
        },
        {
            "license": null,
            "height": 360,
            "date_captured": null,
            "width": 640,
            "dataset": "globalme",
            "id": 17,
            "coco_url": null,
            "flickr_url": null,
            "file_name": "0011.jpg",
            "image": "./img/0011.jpg"
        },
        {
            "license": null,
            "height": 360,
            "date_captured": null,
            "width": 640,
            "dataset": "globalme",
            "id": 18,
            "coco_url": null,
            "flickr_url": null,
            "file_name": "0003.jpg",
            "image": "./img/0003.jpg"
        },
        {
            "license": null,
            "height": 360,
            "date_captured": null,
            "width": 640,
            "dataset": "globalme",
            "id": 19,
            "coco_url": null,
            "flickr_url": null,
            "file_name": "0001.jpg",
            "image": "./img/0001.jpg"
        },
        {
            "license": null,
            "height": 360,
            "date_captured": null,
            "width": 640,
            "dataset": "globalme",
            "id": 20,
            "coco_url": null,
            "flickr_url": null,
            "file_name": "0004.jpg",
            "image": "./img/0004.jpg"
        },
        {
            "license": null,
            "height": 360,
            "date_captured": null,
            "width": 640,
            "dataset": "globalme",
            "id": 21,
            "coco_url": null,
            "flickr_url": null,
            "file_name": "0020.jpg",
            "image": "./img/0020.jpg"
        },
        {
            "license": null,
            "height": 360,
            "date_captured": null,
            "width": 640,
            "dataset": "globalme",
            "id": 22,
            "coco_url": null,
            "flickr_url": null,
            "file_name": "0016.jpg",
            "image": "./img/0016.jpg"
        },
        {
            "license": null,
            "height": 360,
            "date_captured": null,
            "width": 640,
            "dataset": "globalme",
            "id": 23,
            "coco_url": null,
            "flickr_url": null,
            "file_name": "0012.jpg",
            "image": "./img/0012.jpg"
        }
    ],
    "categories": [
        {
            "supercategory": "",
            "id": 0,
            "name": "bg"
        },
        {
            "supercategory": "",
            "id": 1,
            "name": "remote_car"
        }
    ]
}